regulagity/__init__.py
regulagity-0.0.2.dist-info/LICENSE
regulagity-0.0.2.dist-info/METADATA
regulagity-0.0.2.dist-info/WHEEL
regulagity-0.0.2.dist-info/entry_points.txt
regulagity-0.0.2.dist-info/top_level.txt
regulagity-0.0.2.dist-info/RECORD
