Metadata-Version: 2.1
Name: regulagity
Version: 0.0.2
Summary: A tool for measuring the activity of a git repo using a variety of single summary statistics
Home-page: https://github.com/TMiguelT/Regulagity
Author: Michael Milton
Author-email: michael.r.milton@gmail.com
License: UNKNOWN
Keywords: git activity summary
Platform: UNKNOWN
Classifier: Environment :: Console
Classifier: Intended Audience :: Developers
Classifier: License :: OSI Approved :: GNU Lesser General Public License v3 or later (LGPLv3+)
Classifier: Natural Language :: English
Classifier: Operating System :: OS Independent
Classifier: Topic :: Software Development :: Version Control
Classifier: Topic :: Software Development :: Version Control :: Git
Requires-Dist: gitpython
Requires-Dist: click
Requires-Dist: pandas
